imageCS_utils/__init__.py
imageCS_utils/file_writer.py
imageCS_utils/forward_func.py
imageCS_utils/generate_test_ans.py
imageCS_utils/get_matrix.py
imageCS_utils/load_pretrained_model.py
imageCS_utils/old_pretrained_compatible.py
imageCS_utils/psnr_compare.py
imageCS_utils/size_alignment.py
imageCS_utils/text_writer.py
imageCS_utils/transforms.py
imageCS_utils/utils.py
imageCS_utils/YCbCr/__init__.py
imageCS_utils/YCbCr/ycbcr.py
imageCS_utils/base_utils/Logger.py
imageCS_utils/base_utils/__init__.py
imageCS_utils/base_utils/base.py
imageCS_utils/base_utils/cfg_gen.py
imageCS_utils/base_utils/gpu_holder.py
imageCS_utils/base_utils/info.py
imageCS_utils/base_utils/multi_proc.py
imageCS_utils/base_utils/seed.py
imageCS_utils/base_utils/shared_utils.py
imageCS_utils/base_utils/status.py
imageCS_utils/base_utils/trainer.py
imageCS_utils/complexPyTorch/__init__.py
imageCS_utils/complexPyTorch/complexFunctions.py
imageCS_utils/complexPyTorch/complexLayers.py
imageCS_utils/metrics/__init__.py
imageCS_utils/metrics/distribution_test/__init__.py
imageCS_utils/metrics/distribution_test/draw_distribution.py
imageCS_utils/metrics/distribution_test/gaussian_test.py
imageCS_utils/metrics/fid/__init__.py
imageCS_utils/metrics/fid/fid.py
imageCS_utils/metrics/flops/__init__.py
imageCS_utils/metrics/flops/flops.py
imageCS_utils/metrics/lpips/__init__.py
imageCS_utils/metrics/lpips/lpips.py
imageCS_utils/metrics/msssim/__init__.py
imageCS_utils/metrics/msssim/ssim.py
imageCS_utils/metrics/msssim/ssim_skimage.py
imageCS_utils/metrics/noise/__init__.py
imageCS_utils/metrics/noise/noise.py
imageCS_utils/metrics/params/__init__.py
imageCS_utils/metrics/params/params.py
imageCS_utils/metrics/psnr/__init__.py
imageCS_utils/metrics/psnr/psnr.py
imageCS_utils/metrics/time/__init__.py
imageCS_utils/metrics/time/time_tester.py
imageCS_utils/metrics/void/__init__.py
imageCS_utils/metrics/void/void.py
imageCS_utils/torch_dct/__init__.py
imageCS_utils/torch_dct/_dct.py
imagecs_utils-2025.7.10.dist-info/licenses/LICENSE
imagecs_utils-2025.7.10.dist-info/METADATA
imagecs_utils-2025.7.10.dist-info/WHEEL
imagecs_utils-2025.7.10.dist-info/top_level.txt
imagecs_utils-2025.7.10.dist-info/RECORD
