Metadata-Version: 2.4
Name: imageCS_utils
Version: 2025.7.10
Summary: Some useful utils for deep learning (PyTorch) image compressive sensing (CS).
Author-email: Liao Chen <liaochen@bjtu.edu.cn>
Project-URL: Homepage, https://github.com/FengodChen/imageCS-utils
Project-URL: Issues, https://github.com/FengodChen/imageCS-utils/issues
Classifier: Programming Language :: Python :: 3
Classifier: License :: OSI Approved :: MIT License
Classifier: Operating System :: OS Independent
Requires-Python: >=3.10
License-File: LICENSE
Requires-Dist: torch
Requires-Dist: torchvision
Requires-Dist: torchaudio
Requires-Dist: timm
Requires-Dist: einops
Requires-Dist: thop
Requires-Dist: pytorch-fid
Requires-Dist: lpips
Requires-Dist: opencv-python
Requires-Dist: matplotlib
Requires-Dist: scikit-image
Dynamic: license-file
